pretix_cinesend/__init__.py
pretix_cinesend/apps.py
pretix_cinesend/forms.py
pretix_cinesend/models.py
pretix_cinesend/signals.py
pretix_cinesend/tasks.py
pretix_cinesend/urls.py
pretix_cinesend/views.py
pretix_cinesend/locale/django.pot
pretix_cinesend/locale/de/LC_MESSAGES/django.mo
pretix_cinesend/locale/de/LC_MESSAGES/django.po
pretix_cinesend/locale/de_Informal/.gitkeep
pretix_cinesend/locale/de_Informal/LC_MESSAGES/django.mo
pretix_cinesend/locale/de_Informal/LC_MESSAGES/django.po
pretix_cinesend/locale/nl/LC_MESSAGES/django.mo
pretix_cinesend/locale/nl/LC_MESSAGES/django.po
pretix_cinesend/migrations/0001_initial.py
pretix_cinesend/migrations/0002_subeventproduct.py
pretix_cinesend/migrations/__init__.py
pretix_cinesend/static/pretix_cinesend/.gitkeep
pretix_cinesend/static/pretix_cinesend/logo.svg
pretix_cinesend/templates/pretix_cinesend/.gitkeep
pretix_cinesend/templates/pretix_cinesend/order_info.html
pretix_cinesend/templates/pretix_cinesend/settings.html
pretix_cinesend-1.3.0.dist-info/LICENSE
pretix_cinesend-1.3.0.dist-info/METADATA
pretix_cinesend-1.3.0.dist-info/WHEEL
pretix_cinesend-1.3.0.dist-info/entry_points.txt
pretix_cinesend-1.3.0.dist-info/top_level.txt
pretix_cinesend-1.3.0.dist-info/RECORD
