Metadata-Version: 2.1
Name: pretix-cinesend
Version: 1.3.0
Summary: Connects pretix to CineSend
Home-page: https://github.com/pretix/pretix-cinesend
Author: pretix team
Author-email: support@pretix.eu
License: Apache
License-File: LICENSE
